MANIFEST.in
README.rst
requirements.txt
requirements_dev.txt
setup.py
.github/workflows/main.yml
.github/workflows/pypi.yml
biosniff/__init__.py
biosniff/main.py
biosniff/sniffer.py
biosniff.egg-info/PKG-INFO
biosniff.egg-info/SOURCES.txt
biosniff.egg-info/dependency_links.txt
biosniff.egg-info/entry_points.txt
biosniff.egg-info/not-zip-safe
biosniff.egg-info/requires.txt
biosniff.egg-info/top_level.txt
doc/biosniff_logo_256.png