Metadata-Version: 2.1
Name: biosniff
Version: 1.0.0
Summary: A sniffer for biological data formats
Home-page: http://pypi.python.org/pypi/biosniff
Download-URL: http://pypi.python.org/pypi/biosniff
Author: The bioconvert Contributors
Author-email: thomas.cokelaer@pasteur.fr
Maintainer: Thomas Cokelaer
Maintainer-email: thomas.cokelaer@pasteur.fr
License: BSD
Keywords: NGS
Platform: Linux
Platform: Unix
Platform: MacOsX
Platform: Windows
Classifier: Development Status :: 5 - Production/Stable
Classifier: Intended Audience :: Developers
Classifier: Intended Audience :: Science/Research
Classifier: License :: OSI Approved :: BSD License
Classifier: Operating System :: OS Independent
Classifier: Programming Language :: Python :: 3.7
Classifier: Programming Language :: Python :: 3.8
Classifier: Programming Language :: Python :: 3.9
Classifier: Programming Language :: Python :: 3.10
Classifier: Topic :: Software Development :: Libraries :: Python Modules
Classifier: Topic :: Scientific/Engineering :: Bio-Informatics
Classifier: Topic :: Scientific/Engineering :: Information Analysis
